gabriel10/__init__.py
gabriel10_turbobert-0.0.2.dist-info/LICENSE
gabriel10_turbobert-0.0.2.dist-info/METADATA
gabriel10_turbobert-0.0.2.dist-info/WHEEL
gabriel10_turbobert-0.0.2.dist-info/top_level.txt
gabriel10_turbobert-0.0.2.dist-info/RECORD
