Metadata-Version: 2.1
Name: gabriel10-turbobert
Version: 0.0.2
Summary: Very Simple PDF TypeWriter
Home-page: https://github.com/turbobert/gabriel10
Author: Robert Degen
Author-email: os@turbobert.de
License: UNKNOWN
Platform: UNKNOWN
Requires-Python: >=3.6
Requires-Dist: reportlab
Requires-Dist: tabulate
